SlackNotify/__init__.py
fauen_slacknotify-0.0.1.dist-info/licenses/LICENSE
fauen_slacknotify-0.0.1.dist-info/METADATA
fauen_slacknotify-0.0.1.dist-info/WHEEL
fauen_slacknotify-0.0.1.dist-info/top_level.txt
fauen_slacknotify-0.0.1.dist-info/RECORD
