Metadata-Version: 2.4
Name: Fauen-SlackNotify
Version: 0.0.1
Summary: Used to send message using Slack webhook.
Author: Daniel Bäckman
Author-email: daniel@backman.io
Requires-Python: >=3.13.1
License-File: LICENSE
Requires-Dist: requests
Dynamic: author
Dynamic: author-email
Dynamic: license-file
Dynamic: requires-dist
Dynamic: requires-python
Dynamic: summary
